chemdraw/__init__.py
chemdraw/data_types.py
chemdraw/errors.py
chemdraw/drawers/__init__.py
chemdraw/drawers/draw_atom_numbers.py
chemdraw/drawers/draw_atoms.py
chemdraw/drawers/draw_bond_numbers.py
chemdraw/drawers/draw_bonds.py
chemdraw/drawers/draw_debug.py
chemdraw/drawers/draw_highlights.py
chemdraw/drawers/draw_parenthesis.py
chemdraw/drawers/draw_ring_highlights.py
chemdraw/drawers/draw_ring_numbers.py
chemdraw/drawers/draw_title.py
chemdraw/drawers/drawer.py
chemdraw/drawers/drawer_gif.py
chemdraw/drawers/drawer_grid.py
chemdraw/drawers/general_classes.py
chemdraw/drawers/layout.py
chemdraw/objects/__init__.py
chemdraw/objects/atoms.py
chemdraw/objects/bonds.py
chemdraw/objects/molecule.py
chemdraw/objects/parenthesis.py
chemdraw/objects/polymer.py
chemdraw/objects/rings.py
chemdraw/utils/__init__.py
chemdraw/utils/decorators.py
chemdraw/utils/general_math.py
chemdraw/utils/graph_algorithms.py
chemdraw/utils/mole_file_parser.py
chemdraw/utils/shapes.py
chemdraw/utils/vector_math.py
chemdraw-0.0.6.dist-info/LICENSE.txt
chemdraw-0.0.6.dist-info/METADATA
chemdraw-0.0.6.dist-info/WHEEL
chemdraw-0.0.6.dist-info/top_level.txt
chemdraw-0.0.6.dist-info/RECORD
