Metadata-Version: 2.1
Name: chemdraw
Version: 0.0.6
Summary: Drawing molecules
Home-page: https://github.com/dylanwal/chemdraw
Author: Dylan Walsh
License: BSD
Platform: any
Classifier: License :: OSI Approved :: BSD License
Classifier: Programming Language :: Python :: 3
Classifier: Programming Language :: Python :: 3 :: Only
Classifier: Programming Language :: Python :: 3.10
Requires-Python: >=3.10
License-File: LICENSE.txt
Requires-Dist: numpy>=1.23.1
Requires-Dist: plotly>=5.9.0
Requires-Dist: kaleido>=0.1.0
Requires-Dist: rdkit>=2022.3.4
Requires-Dist: Pillow>=9.2.0
Requires-Dist: scikit-learn>=1.1.1
